{
    "x": 0,
    "y": 300,
    "description": "Walk to DevOps / IT pod",
    "actions": {
        "exit": {
            "poke": [
                {
                    "action": "setHoverText",
                    "text": ""
                },
                {
                    "action": "travel",
                    "location": "devops"
                }    
            ]
        }
    },
    "current-state": "exit",
    "states": {
        "exit": {
            "image": "left-right-exit"
        }
    }
}
